odoo/addons/website_anchor_smooth_scroll/README.rst
odoo/addons/website_anchor_smooth_scroll/__init__.py
odoo/addons/website_anchor_smooth_scroll/__manifest__.py
odoo/addons/website_anchor_smooth_scroll/demo/pages.xml
odoo/addons/website_anchor_smooth_scroll/i18n/bg.po
odoo/addons/website_anchor_smooth_scroll/i18n/de.po
odoo/addons/website_anchor_smooth_scroll/i18n/es.po
odoo/addons/website_anchor_smooth_scroll/i18n/fr.po
odoo/addons/website_anchor_smooth_scroll/i18n/it.po
odoo/addons/website_anchor_smooth_scroll/i18n/pt_BR.po
odoo/addons/website_anchor_smooth_scroll/i18n/sl.po
odoo/addons/website_anchor_smooth_scroll/static/description/icon.png
odoo/addons/website_anchor_smooth_scroll/static/src/js/website_anchor_smooth_scroll.js
odoo/addons/website_anchor_smooth_scroll/views/assets.xml
odoo11_addon_website_anchor_smooth_scroll-11.0.1.0.0.dist-info/DESCRIPTION.rst
odoo11_addon_website_anchor_smooth_scroll-11.0.1.0.0.dist-info/METADATA
odoo11_addon_website_anchor_smooth_scroll-11.0.1.0.0.dist-info/RECORD
odoo11_addon_website_anchor_smooth_scroll-11.0.1.0.0.dist-info/WHEEL
odoo11_addon_website_anchor_smooth_scroll-11.0.1.0.0.dist-info/metadata.json
odoo11_addon_website_anchor_smooth_scroll-11.0.1.0.0.dist-info/top_level.txt
